plotly_ml/__init__.py
plotly_ml/regression.py
plotly_ml/univariant.py
plotly_ml/utils/__init__.py
plotly_ml/utils/colors.py
plotly_ml/utils/metrics.py
plotly_ml-0.1.17.dist-info/METADATA
plotly_ml-0.1.17.dist-info/WHEEL
plotly_ml-0.1.17.dist-info/top_level.txt
plotly_ml-0.1.17.dist-info/RECORD
