Metadata-Version: 2.4
Name: plotly-ml
Version: 0.1.17
Summary: Interactive ML Visualizations with Plotly
Classifier: Development Status :: 5 - Production/Stable
Classifier: Programming Language :: Python :: 3.9
Classifier: Programming Language :: Python :: 3.10
Classifier: Programming Language :: Python :: 3.11
Classifier: Programming Language :: Python :: 3.12
Classifier: Programming Language :: Python :: 3.13
Classifier: Topic :: Scientific/Engineering :: Visualization
Classifier: License :: OSI Approved :: MIT License
Requires-Python: >=3.9
Requires-Dist: ipykernel>=6.30.1
Requires-Dist: ipywidgets>=8.1.7
Requires-Dist: pandas>=2.3.2
Requires-Dist: plotly>=6.3.0
Requires-Dist: polars>=1.33.1
Provides-Extra: docs
Requires-Dist: mkdocs>=1.6.1; extra == "docs"
Requires-Dist: mkdocs-material>=9.6.20; extra == "docs"
Requires-Dist: mkdocstrings[python]>=0.30.1; extra == "docs"
Requires-Dist: mkdocs-autorefs>=1.4.3; extra == "docs"
